{"cameraMode":{"drawMode":0,"name":"Shaded","section":"Shading Mode"},"sceneLighting":true,"audioPlay":false,"sceneViewState":{"showFog":true,"showMaterialUpdate":false,"showSkybox":true,"showFlares":true,"showImageEffects":true,"showParticleSystems":true},"in2DMode":false,"pivot":{"x":-3.518033266067505,"y":-1.5155868530273438,"z":4.075055122375488},"rotation":{"x":-0.26413819193840029,"y":-0.001747335190884769,"z":0.0004780642339028418,"w":-0.9644831418991089},"size":32.18387222290039,"orthographic":false}